{"state":"Perak","season_id":11,"state_id":8,"seat_id":"P069","seat_name":"PARIT","is_heavyweight":0,"registered_voters":47915,"rejected_votes":0,"official_result":true,"last_published_at":"2022-11-19T19:23:14.000000Z","majority":2155,"candidates":[{"name":"MUHAMMAD ISMI MAT TAIB","status":"win","vote":17181,"party":55,"id":1557},{"name":"MOHD NIZAR ZAKARIA","status":"lose","vote":15026,"party":1,"id":428},{"name":"NURTHAQAFFAH NORDIN","status":"lose","vote":5063,"party":42,"id":4595},{"name":"FAIZOL FADZLI MOHAMED","status":"lose","vote":275,"party":57,"id":4601}]}
