{"state":"Sabah","season_id":1,"state_id":12,"seat_id":"P175","seat_name":"PAPAR","is_heavyweight":0,"registered_voters":43586,"rejected_votes":543,"official_result":true,"last_published_at":"2021-11-14T18:30:40.000000Z","majority":325,"candidates":[{"name":"AHMAD HASSAN","status":"win","vote":17394,"party":33,"id":661},{"name":"ROSNAH ABD RASHID SHIRLIN","status":"lose","vote":17069,"party":1,"id":663},{"name":"JAMIL WILLIAM CORE","status":"lose","vote":892,"party":35,"id":664},{"name":"ELBERT SIKUIL","status":"lose","vote":481,"party":32,"id":660}]}
